[
    {
        "subType": "Sauvignon Blanc",
        "type": "Dry White",
        "description": [
            "bright",
            "crisp",
            "refreshing"
        ],
        "country": "France"
    },
    {
        "subType": "Gr端ner Veltliner",
        "type": "Dry White",
        "description": [
            "zesty",
            "heat",
            "summer"
        ],
        "country": "Austria"
    },
    {
        "subType": "Pinot Grigio",
        "type": "Dry White",
        "description": [
            "",
            "",
            ""
        ],
        "country": ""
    },
    {
        "subType": "Albari単o",
        "type": "Dry White",
        "description": [
            "mountain",
            "romance",
            "king"
        ],
        "country": "Spain"
    },
    {
        "subType": "Gew端rztraminer",
        "type": "Sweet White",
        "description": [
            "",
            "",
            ""
        ],
        "country": ""
    },
    {
        "subType": "M端ller-Thurgau",
        "type": "Sweet White",
        "description": [
            "",
            "",
            ""
        ],
        "country": ""
    },
    {
        "subType": "Malvasia",
        "type": "Sweet White",
        "description": [
            "",
            "",
            ""
        ],
        "country": ""
    },
    {
        "subType": "Moscato",
        "type": "Sweet White",
        "description": [
            "",
            "",
            ""
        ],
        "country": ""
    },
    {
        "subType": "Riesling",
        "type": "Sweet White",
        "description": [
            "medieval",
            "estate",
            "villa"
        ],
        "country": "Germany"
    },
    {
        "subType": "Chardonnay",
        "type": "Rich White",
        "description": [
            "sensual",
            "flirt",
            "rich"
        ],
        "country": ""
    },
    {
        "subType": "Roussanne",
        "type": "Rich White",
        "description": [
            "",
            "",
            ""
        ],
        "country": ""
    },
    {
        "subType": "Marsanne",
        "type": "Rich White",
        "description": [
            "",
            "",
            ""
        ],
        "country": ""
    },
    {
        "subType": "Viognier",
        "type": "Rich White",
        "description": [
            "",
            "",
            ""
        ],
        "country": ""
    },
    {
        "subType": "Champagne",
        "type": "Sparkling",
        "description": [
            "",
            "",
            ""
        ],
        "country": ""
    },
    {
        "subType": "Prosecco",
        "type": "Sparkling",
        "description": [
            "",
            "",
            ""
        ],
        "country": ""
    },
    {
        "subType": "Cava",
        "type": "Sparkling",
        "description": [
            "",
            "",
            ""
        ],
        "country": ""
    },
    {
        "subType": "St. Laurent",
        "type": "Light Red",
        "description": [
            "",
            "",
            ""
        ],
        "country": ""
    },
    {
        "subType": "Pinot Noir",
        "type": "Light Red",
        "description": [
            "",
            "",
            ""
        ],
        "country": ""
    },
    {
        "subType": "Zweigelt",
        "type": "Light Red",
        "description": [
            "",
            "",
            ""
        ],
        "country": ""
    },
    {
        "subType": "Gamay",
        "type": "Light Red",
        "description": [
            "",
            "",
            ""
        ],
        "country": ""
    },
    {
        "subType": "Tempranillo",
        "type": "Medium Red",
        "description": [
            "",
            "",
            ""
        ],
        "country": ""
    },
    {
        "subType": "Sangiovese",
        "type": "Medium Red",
        "description": [
            "",
            "",
            ""
        ],
        "country": ""
    },
    {
        "subType": "Zinfandel",
        "type": "Medium Red",
        "description": [
            "",
            "",
            ""
        ],
        "country": ""
    },
    {
        "subType": "Grenache",
        "type": "Medium Red",
        "description": [
            "",
            "",
            ""
        ],
        "country": ""
    },
    {
        "subType": "Merlot",
        "type": "Medium Red",
        "description": [
            "",
            "",
            ""
        ],
        "country": ""
    },
    {
        "subType": "Cabernet Sauvignon",
        "type": "Bold Red",
        "description": [
            "",
            "",
            ""
        ],
        "country": ""
    },
    {
        "subType": "Monastrell",
        "type": "Bold Red",
        "description": [
            "",
            "",
            ""
        ],
        "country": ""
    },
    {
        "subType": "Aglianico",
        "type": "Bold Red",
        "description": [
            "",
            "",
            ""
        ],
        "country": ""
    },
    {
        "subType": "Malbec",
        "type": "Bold Red",
        "description": [
            "adventure",
            "quest",
            "hero"
        ],
        "country": "Argentina"
    },
    {
        "subType": "Syrah",
        "type": "Bold Red",
        "description": [
            "",
            "",
            ""
        ],
        "country": ""
    },
    {
        "subType": "Late Harvest",
        "type": "Dessert",
        "description": [
            "",
            "",
            ""
        ],
        "country": ""
    },
    {
        "subType": "Ice Wine",
        "type": "Dessert",
        "description": [
            "",
            "",
            ""
        ],
        "country": ""
    },
    {
        "subType": "Sherry",
        "type": "Dessert",
        "description": [
            "",
            "",
            ""
        ],
        "country": ""
    },
    {
        "subType": "Port",
        "type": "Dessert",
        "description": [
            "",
            "",
            ""
        ],
        "country": ""
    }
]